material_color/__init__.py
material_color/color.py
material_color/resources/__init__.py
material_color/resources/material-colors.json
material_color-1.1.0.dist-info/LICENSE
material_color-1.1.0.dist-info/WHEEL
material_color-1.1.0.dist-info/METADATA
material_color-1.1.0.dist-info/RECORD
